MANIFEST.in
setup.py
microdev/__init__.py
microdev/context_processors.py
microdev/decorators.py
microdev/forms.py
microdev/handlers.py
microdev/models.py
microdev/tasks.py
microdev/utils.py
microdev.egg-info/PKG-INFO
microdev.egg-info/SOURCES.txt
microdev.egg-info/dependency_links.txt
microdev.egg-info/requires.txt
microdev.egg-info/top_level.txt
microdev/cached/__init__.py
microdev/cached/models.py
microdev/csv/__init__.py
microdev/csv/forms.py
microdev/csv/models.py
microdev/csv/utils.py
microdev/csv/migrations/0001_initial.py
microdev/csv/migrations/__init__.py
microdev/google_client_api/__init__.py
microdev/google_client_api/models.py
microdev/google_client_api/migrations/0001_initial.py
microdev/google_client_api/migrations/__init__.py
microdev/migrations/0001_initial.py
microdev/migrations/__init__.py
microdev/postal_address/__init__.py
microdev/postal_address/forms.py
microdev/postal_address/models.py
microdev/postal_address/migrations/0001_initial.py
microdev/postal_address/migrations/__init__.py
microdev/templates/microdev/show_errors.html
microdev/templatetags/__init__.py
microdev/templatetags/microdev_tags.py