Metadata-Version: 1.1
Name: microdev
Version: 0.0.11
Summary: A collection of simple reusable Django utility modules.
Home-page: https://github.com/kdmukai/microdev
Author: Keith Mukai
Author-email: keith.mukai@essaytagger.com
License: BSD
Keywords: example documentation tutorial
Platform: UNKNOWN
Classifier: Development Status :: 5 - Production/Stable
Classifier: Topic :: Utilities
Classifier: License :: OSI Approved :: BSD License
